{
  "title": "About Jay Doesitall — Personal Trainer & Running Expert",
  "description": "Meet Jérémie “Jay” Seck: certified personal trainer and running coach. Vision, values and training philosophy.",
  "alternates": {
    "canonical": "https://jaydoesitall.com/en/about",
    "languages": {
      "en": "https://jaydoesitall.com/en/about",
      "fr": "https://jaydoesitall.com/fr/about"
    }
  },
  "keywords": [
    "about Jay Doesitall",
    "personal trainer bio",
    "running coach Paris",
    "training philosophy",
    "Hyrox Spartan athlete",
    "performance coaching"
  ],
  "openGraph": {
    "title": "About — Jay Doesitall",
    "description": "Personal trainer & running expert. Sustainable progress and joy in the effort.",
    "type": "website",
    "locale": "en_US",
    "url": "https://jaydoesitall.com/en/about",
    "images": [
      {
        "url": "https://jaydoesitall.com/seed/about_hero.png",
        "width": 1200,
        "height": 630,
        "alt": "About Jay Doesitall"
      }
    ]
  },
  "twitter": {
    "card": "summary_large_image",
    "title": "About — Jay Doesitall",
    "description": "Certified personal trainer & running coach in Paris and online.",
    "images": ["https://jaydoesitall.com/seed/about_hero.png"]
  },
  "robots": { "index": true, "follow": true, "max-image-preview": "large" }
}
